test_meta_app/__init__.py
test_meta_app-0.1.0.dist-info/METADATA
test_meta_app-0.1.0.dist-info/WHEEL
test_meta_app-0.1.0.dist-info/RECORD
