Metadata-Version: 2.3
Name: test-meta-app
Version: 0.1.0
Summary: A meta-package that installs another package
License: MIT
Author: Your Name
Author-email: your@email.com
Requires-Python: >=3.9,<4.0
Classifier: License :: OSI Approved :: MIT License
Classifier: Programming Language :: Python :: 3
Classifier: Programming Language :: Python :: 3.9
Classifier: Programming Language :: Python :: 3.10
Classifier: Programming Language :: Python :: 3.11
Classifier: Programming Language :: Python :: 3.12
Classifier: Programming Language :: Python :: 3.13
Requires-Dist: writer-sdk (>=1.6.0,<2.0.0)
